README.md
setup.py
GeneSGAN/Gene_SGAN_clustering.py
GeneSGAN/__init__.py
GeneSGAN/clustering.py
GeneSGAN/data_loading.py
GeneSGAN/evaluate.py
GeneSGAN/model.py
GeneSGAN/modules.py
GeneSGAN/networks.py
GeneSGAN/utils.py
GeneSGAN.egg-info/PKG-INFO
GeneSGAN.egg-info/SOURCES.txt
GeneSGAN.egg-info/dependency_links.txt
GeneSGAN.egg-info/requires.txt
GeneSGAN.egg-info/top_level.txt