Metadata-Version: 2.1
Name: GeneSGAN
Version: 0.0.2
Summary: A python implementation of Gene-SGAN for multi-view semi-supervised clustering
Home-page: https://github.com/zhijian-yang/GeneSGAN
Author: zhijian.yang
Author-email: zhijianyang@outlook.com
Classifier: Programming Language :: Python :: 3
Classifier: License :: OSI Approved :: MIT License
Classifier: Operating System :: OS Independent
